my_tool_package/__init__.py
my_tool_package/connections.py
my_tool_package/tools/__init__.py
my_tool_package/tools/my_tool_1.py
my_tool_package/tools/my_tool_2.py
my_tool_package/tools/my_tool_with_custom_strong_type_connection.py
my_tool_package/tools/utils.py
my_tool_package/yamls/my_tool_1.yaml
my_tool_package/yamls/my_tool_2.yaml
my_tool_package/yamls/my_tool_with_custom_strong_type_connection.yaml
tests/__init__.py
tests/test_my_tool_1.py
tests/test_my_tool_2.py
tests/test_my_tool_with_custom_strong_type_connection.py
test_custom_tools-0.0.2.dist-info/METADATA
test_custom_tools-0.0.2.dist-info/WHEEL
test_custom_tools-0.0.2.dist-info/entry_points.txt
test_custom_tools-0.0.2.dist-info/top_level.txt
test_custom_tools-0.0.2.dist-info/RECORD
