Metadata-Version: 2.1
Name: test-custom-tools
Version: 0.0.2
Summary: This is test tools package with custom strong type connection.
